ZetcodeSpringBootJiaochengChuyi/README.md
ZetcodeSpringBootJiaochengChuyi/__init__.py
ZetcodeSpringBootJiaochengChuyi/__main__.py
ZetcodeSpringBootJiaochengChuyi/file.epub
ZetcodeSpringBootJiaochengChuyi/index.html
ZetcodeSpringBootJiaochengChuyi/css/__init__.py
ZetcodeSpringBootJiaochengChuyi/css/annotations.css
ZetcodeSpringBootJiaochengChuyi/css/main.css
ZetcodeSpringBootJiaochengChuyi/css/normalize.css
ZetcodeSpringBootJiaochengChuyi/css/popup.css
ZetcodeSpringBootJiaochengChuyi/font/__init__.py
ZetcodeSpringBootJiaochengChuyi/font/fontello.eot
ZetcodeSpringBootJiaochengChuyi/font/fontello.svg
ZetcodeSpringBootJiaochengChuyi/font/fontello.ttf
ZetcodeSpringBootJiaochengChuyi/font/fontello.woff
ZetcodeSpringBootJiaochengChuyi/img/__init__.py
ZetcodeSpringBootJiaochengChuyi/img/annotator-glyph-sprite.png
ZetcodeSpringBootJiaochengChuyi/img/annotator-icon-sprite.png
ZetcodeSpringBootJiaochengChuyi/img/apple-touch-icon.png
ZetcodeSpringBootJiaochengChuyi/img/cancelfullscreen.png
ZetcodeSpringBootJiaochengChuyi/img/close.png
ZetcodeSpringBootJiaochengChuyi/img/fullscreen.png
ZetcodeSpringBootJiaochengChuyi/img/loader.gif
ZetcodeSpringBootJiaochengChuyi/img/menu-icon.png
ZetcodeSpringBootJiaochengChuyi/img/save.png
ZetcodeSpringBootJiaochengChuyi/img/saved.png
ZetcodeSpringBootJiaochengChuyi/img/settings-s.png
ZetcodeSpringBootJiaochengChuyi/img/settings.png
ZetcodeSpringBootJiaochengChuyi/img/star.png
ZetcodeSpringBootJiaochengChuyi/js/__init__.py
ZetcodeSpringBootJiaochengChuyi/js/epub.js
ZetcodeSpringBootJiaochengChuyi/js/epub.min.js
ZetcodeSpringBootJiaochengChuyi/js/epub.min.map
ZetcodeSpringBootJiaochengChuyi/js/hooks.min.js
ZetcodeSpringBootJiaochengChuyi/js/hooks.min.map
ZetcodeSpringBootJiaochengChuyi/js/reader.js
ZetcodeSpringBootJiaochengChuyi/js/reader.js.map
ZetcodeSpringBootJiaochengChuyi/js/reader.min.js
ZetcodeSpringBootJiaochengChuyi/js/reader.min.map
ZetcodeSpringBootJiaochengChuyi/js/hooks/__init__.py
zetcode_spring_boot_jiaocheng_chuyi-2024.3.5.0.dist-info/METADATA
zetcode_spring_boot_jiaocheng_chuyi-2024.3.5.0.dist-info/WHEEL
zetcode_spring_boot_jiaocheng_chuyi-2024.3.5.0.dist-info/entry_points.txt
zetcode_spring_boot_jiaocheng_chuyi-2024.3.5.0.dist-info/top_level.txt
zetcode_spring_boot_jiaocheng_chuyi-2024.3.5.0.dist-info/RECORD
